textgenie/__init__.py
textgenie/grammar_utils.py
textgenie/textgenie.py
textgenie-0.1.9.7.dist-info/LICENSE
textgenie-0.1.9.7.dist-info/METADATA
textgenie-0.1.9.7.dist-info/WHEEL
textgenie-0.1.9.7.dist-info/top_level.txt
textgenie-0.1.9.7.dist-info/RECORD
