Metadata-Version: 2.1
Name: textgenie
Version: 0.1.9.7
Summary: A python library to augment text data using NLP.
Home-page: http://github.com/hetpandya/TextGenie
Author: Het Pandya
Author-email: hetpandya6797@gmail.com
License: MIT
Platform: UNKNOWN
License-File: LICENSE
Requires-Dist: torch (>=1.5.0)
Requires-Dist: transformers
Requires-Dist: sentencepiece
Requires-Dist: spacy
Requires-Dist: tqdm
Requires-Dist: pandas
Requires-Dist: pattern (==3.6)
